my_aws_cloud/__init__.py
my_aws_cloud/comp.py
my_aws_cloud/db.py
my_aws_cloud/store.py
my_aws_cloud-0.0.1.dist-info/METADATA
my_aws_cloud-0.0.1.dist-info/WHEEL
my_aws_cloud-0.0.1.dist-info/top_level.txt
my_aws_cloud-0.0.1.dist-info/RECORD
