Metadata-Version: 2.1
Name: my-aws-cloud
Version: 0.0.1
Summary: My first package
Home-page: https://github.com/kushagra.mittal/my-aws-cloud
Author: kush
Author-email: kushagra.mittal@ihsmarkit.com
License: MIT
Requires-Python: >=3.8
